Metadata-Version: 2.1
Name: solverecaptchas
Version: 0.1.4
Summary: An asynchronized Python library to automate solving ReCAPTCHA v2
Home-page: https://github.com/embium/solverecaptchas
Author: Michael Mooney <me@mikey.id>
Author-email: me@mikey.id
License: GPL-3.0
Platform: all
Classifier: Development Status :: 4 - Beta
Classifier: Intended Audience :: Developers
Classifier: Intended Audience :: Science/Research
Classifier: License :: OSI Approved :: GNU General Public License v3 (GPLv3)
Classifier: Natural Language :: English
Classifier: Operating System :: OS Independent
Classifier: Programming Language :: Python :: 3
Classifier: Programming Language :: Python :: 3.7
Classifier: Programming Language :: Python :: 3.8
Classifier: Programming Language :: JavaScript
Classifier: Topic :: Scientific/Engineering
Classifier: Topic :: Software Development :: Libraries
Classifier: Topic :: Utilities
